{
  "USDCHF": {
    "pair": "USDCHF",
    "n_states": 6,
    "covariance_type": "full",
    "score": 126448.42303894827,
    "bic": -3095962351.9617224,
    "aic": -3095963011.6856093,
    "regime_map": {
      "5": "Bull Trend",
      "1": "Bear Trend",
      "2": "High Volatility Expansion",
      "0": "Low Volatility Compression",
      "3": "Value Gap Formation",
      "4": "Mean Reversion Range"
    },
    "n_samples": 12242
  },
  "GBPUSD": {
    "pair": "GBPUSD",
    "n_states": 3,
    "covariance_type": "full",
    "score": 127515.19391061722,
    "bic": -3117236100.951334,
    "aic": -3117236360.3389487,
    "regime_map": {
      "0": "Bull Trend",
      "2": "Bear Trend",
      "1": "High Volatility Expansion"
    },
    "n_samples": 12223
  },
  "EURUSD": {
    "pair": "EURUSD",
    "n_states": 10,
    "covariance_type": "full",
    "score": 127590.05076465862,
    "bic": -3120595682.8161488,
    "aic": -3120597083.6020207,
    "regime_map": {
      "2": "Bull Trend",
      "1": "Bear Trend",
      "8": "High Volatility Expansion",
      "0": "Low Volatility Compression",
      "4": "Value Gap Formation",
      "3": "Mean Reversion Range",
      "5": "Noise",
      "6": "Noise",
      "7": "Noise",
      "9": "Noise"
    },
    "n_samples": 12229
  },
  "USDJPY": {
    "pair": "USDJPY",
    "n_states": 6,
    "covariance_type": "full",
    "score": 123808.84512330496,
    "bic": -3022173072.005387,
    "aic": -3022173731.459874,
    "regime_map": {
      "0": "Bull Trend",
      "5": "Bear Trend",
      "1": "High Volatility Expansion",
      "2": "Low Volatility Compression",
      "3": "Value Gap Formation",
      "4": "Mean Reversion Range"
    },
    "n_samples": 12205
  }
}